{"trial_id": "0a416c15a24aa876207c576485ca929e", "hyperparameters": {"space": [{"class_name": "Boolean", "config": {"name": "structured_data_block_1/normalize", "default": false, "conditions": []}}, {"class_name": "Boolean", "config": {"name": "structured_data_block_1/dense_block_1/use_batchnorm", "default": false, "conditions": []}}, {"class_name": "Choice", "config": {"name": "structured_data_block_1/dense_block_1/num_layers", "default": 2, "conditions": [], "values": [1, 2, 3], "ordered": true}}, {"class_name": "Choice", "config": {"name": "structured_data_block_1/dense_block_1/units_0", "default": 32, "conditions": [], "values": [16, 32, 64, 128, 256, 512, 1024], "ordered": true}}, {"class_name": "Choice", "config": {"name": "structured_data_block_1/dense_block_1/dropout", "default": 0.0, "conditions": [], "values": [0.0, 0.25, 0.5], "ordered": true}}, {"class_name": "Choice", "config": {"name": "structured_data_block_1/dense_block_1/units_1", "default": 32, "conditions": [], "values": [16, 32, 64, 128, 256, 512, 1024], "ordered": true}}, {"class_name": "Choice", "config": {"name": "regression_head_1/dropout", "default": 0, "conditions": [], "values": [0.0, 0.25, 0.5], "ordered": true}}, {"class_name": "Choice", "config": {"name": "optimizer", "default": "adam", "conditions": [], "values": ["adam", "sgd", "adam_weight_decay"], "ordered": false}}, {"class_name": "Choice", "config": {"name": "learning_rate", "default": 0.001, "conditions": [], "values": [0.1, 0.01, 0.001, 0.0001, 2e-05, 1e-05], "ordered": true}}], "values": {"structured_data_block_1/normalize": true, "structured_data_block_1/dense_block_1/use_batchnorm": false, "structured_data_block_1/dense_block_1/num_layers": 1, "structured_data_block_1/dense_block_1/units_0": 32, "structured_data_block_1/dense_block_1/dropout": 0, "structured_data_block_1/dense_block_1/units_1": 32, "regression_head_1/dropout": 0.25, "optimizer": "adam", "learning_rate": 0.001}}, "metrics": {"metrics": {"loss": {"direction": "min", "observations": [{"value": [318.0552062988281], "step": 0}, {"value": [31.477487564086914], "step": 1}, {"value": [26.941747665405273], "step": 2}, {"value": [24.15802001953125], "step": 3}, {"value": [21.9996337890625], "step": 4}, {"value": [20.30036735534668], "step": 5}, {"value": [18.80097198486328], "step": 6}, {"value": [17.73323631286621], "step": 7}, {"value": [16.826740264892578], "step": 8}, {"value": [16.458351135253906], "step": 9}, {"value": [15.93252944946289], "step": 10}, {"value": [15.668143272399902], "step": 11}]}, "mean_squared_error": {"direction": "min", "observations": [{"value": [318.0552062988281], "step": 0}, {"value": [31.477487564086914], "step": 1}, {"value": [26.941747665405273], "step": 2}, {"value": [24.15802001953125], "step": 3}, {"value": [21.9996337890625], "step": 4}, {"value": [20.30036735534668], "step": 5}, {"value": [18.80097198486328], "step": 6}, {"value": [17.73323631286621], "step": 7}, {"value": [16.826740264892578], "step": 8}, {"value": [16.458351135253906], "step": 9}, {"value": [15.93252944946289], "step": 10}, {"value": [15.668143272399902], "step": 11}]}, "val_loss": {"direction": "min", "observations": [{"value": [8.715901374816895], "step": 0}, {"value": [6.95950984954834], "step": 1}, {"value": [7.634561061859131], "step": 2}, {"value": [8.070380210876465], "step": 3}, {"value": [7.690486431121826], "step": 4}, {"value": [8.521285057067871], "step": 5}, {"value": [8.315240859985352], "step": 6}, {"value": [8.153169631958008], "step": 7}, {"value": [7.483787536621094], "step": 8}, {"value": [7.340445518493652], "step": 9}, {"value": [7.462532997131348], "step": 10}, {"value": [7.4095964431762695], "step": 11}]}, "val_mean_squared_error": {"direction": "min", "observations": [{"value": [8.715901374816895], "step": 0}, {"value": [6.95950984954834], "step": 1}, {"value": [7.634561061859131], "step": 2}, {"value": [8.070380210876465], "step": 3}, {"value": [7.690486431121826], "step": 4}, {"value": [8.521285057067871], "step": 5}, {"value": [8.315240859985352], "step": 6}, {"value": [8.153169631958008], "step": 7}, {"value": [7.483787536621094], "step": 8}, {"value": [7.340445518493652], "step": 9}, {"value": [7.462532997131348], "step": 10}, {"value": [7.4095964431762695], "step": 11}]}}}, "score": 6.95950984954834, "best_step": 1, "status": "COMPLETED"}