{"trial_id": "5b4da192f9f6cf553ae54b57a997378e", "hyperparameters": {"space": [{"class_name": "Boolean", "config": {"name": "structured_data_block_1/normalize", "default": false, "conditions": []}}, {"class_name": "Boolean", "config": {"name": "structured_data_block_1/dense_block_1/use_batchnorm", "default": false, "conditions": []}}, {"class_name": "Choice", "config": {"name": "structured_data_block_1/dense_block_1/num_layers", "default": 2, "conditions": [], "values": [1, 2, 3], "ordered": true}}, {"class_name": "Choice", "config": {"name": "structured_data_block_1/dense_block_1/units_0", "default": 32, "conditions": [], "values": [16, 32, 64, 128, 256, 512, 1024], "ordered": true}}, {"class_name": "Choice", "config": {"name": "structured_data_block_1/dense_block_1/dropout", "default": 0.0, "conditions": [], "values": [0.0, 0.25, 0.5], "ordered": true}}, {"class_name": "Choice", "config": {"name": "structured_data_block_1/dense_block_1/units_1", "default": 32, "conditions": [], "values": [16, 32, 64, 128, 256, 512, 1024], "ordered": true}}, {"class_name": "Choice", "config": {"name": "regression_head_1/dropout", "default": 0, "conditions": [], "values": [0.0, 0.25, 0.5], "ordered": true}}, {"class_name": "Choice", "config": {"name": "optimizer", "default": "adam", "conditions": [], "values": ["adam", "sgd", "adam_weight_decay"], "ordered": false}}, {"class_name": "Choice", "config": {"name": "learning_rate", "default": 0.001, "conditions": [], "values": [0.1, 0.01, 0.001, 0.0001, 2e-05, 1e-05], "ordered": true}}, {"class_name": "Choice", "config": {"name": "structured_data_block_1/dense_block_1/units_2", "default": 32, "conditions": [], "values": [16, 32, 64, 128, 256, 512, 1024], "ordered": true}}], "values": {"structured_data_block_1/normalize": true, "structured_data_block_1/dense_block_1/use_batchnorm": false, "structured_data_block_1/dense_block_1/num_layers": 2, "structured_data_block_1/dense_block_1/units_0": 1024, "structured_data_block_1/dense_block_1/dropout": 0, "structured_data_block_1/dense_block_1/units_1": 16, "regression_head_1/dropout": 0.0, "optimizer": "adam_weight_decay", "learning_rate": 0.001, "structured_data_block_1/dense_block_1/units_2": 1024}}, "metrics": {"metrics": {"loss": {"direction": "min", "observations": [{"value": [1484.5472412109375], "step": 0}, {"value": [14.482085227966309], "step": 1}, {"value": [11.795585632324219], "step": 2}, {"value": [15.606308937072754], "step": 3}, {"value": [11.646773338317871], "step": 4}, {"value": [10.152348518371582], "step": 5}, {"value": [9.270550727844238], "step": 6}, {"value": [8.433497428894043], "step": 7}, {"value": [8.874157905578613], "step": 8}, {"value": [7.230831146240234], "step": 9}, {"value": [4.496718883514404], "step": 10}, {"value": [3.739691972732544], "step": 11}, {"value": [3.349414348602295], "step": 12}, {"value": [2.444183111190796], "step": 13}, {"value": [1.9125632047653198], "step": 14}, {"value": [1.8158751726150513], "step": 15}, {"value": [1.4664448499679565], "step": 16}, {"value": [1.1609859466552734], "step": 17}, {"value": [1.1099236011505127], "step": 18}, {"value": [0.8853487372398376], "step": 19}, {"value": [0.7729915976524353], "step": 20}, {"value": [0.5542142391204834], "step": 21}, {"value": [0.5385535955429077], "step": 22}, {"value": [0.4920091927051544], "step": 23}, {"value": [0.3851182758808136], "step": 24}, {"value": [0.2922526001930237], "step": 25}, {"value": [0.2448936104774475], "step": 26}, {"value": [0.23026975989341736], "step": 27}, {"value": [0.19438979029655457], "step": 28}, {"value": [0.1796294003725052], "step": 29}]}, "mean_squared_error": {"direction": "min", "observations": [{"value": [1484.5472412109375], "step": 0}, {"value": [14.482085227966309], "step": 1}, {"value": [11.795585632324219], "step": 2}, {"value": [15.606308937072754], "step": 3}, {"value": [11.646773338317871], "step": 4}, {"value": [10.152348518371582], "step": 5}, {"value": [9.270550727844238], "step": 6}, {"value": [8.433497428894043], "step": 7}, {"value": [8.874157905578613], "step": 8}, {"value": [7.230831146240234], "step": 9}, {"value": [4.496718883514404], "step": 10}, {"value": [3.739691972732544], "step": 11}, {"value": [3.349414348602295], "step": 12}, {"value": [2.444183111190796], "step": 13}, {"value": [1.9125632047653198], "step": 14}, {"value": [1.8158751726150513], "step": 15}, {"value": [1.4664448499679565], "step": 16}, {"value": [1.1609859466552734], "step": 17}, {"value": [1.1099236011505127], "step": 18}, {"value": [0.8853487372398376], "step": 19}, {"value": [0.7729915976524353], "step": 20}, {"value": [0.5542142391204834], "step": 21}, {"value": [0.5385535955429077], "step": 22}, {"value": [0.4920091927051544], "step": 23}, {"value": [0.3851182758808136], "step": 24}, {"value": [0.2922526001930237], "step": 25}, {"value": [0.2448936104774475], "step": 26}, {"value": [0.23026975989341736], "step": 27}, {"value": [0.19438979029655457], "step": 28}, {"value": [0.1796294003725052], "step": 29}]}, "val_loss": {"direction": "min", "observations": [{"value": [14.118906021118164], "step": 0}, {"value": [57.84541320800781], "step": 1}, {"value": [7.574304103851318], "step": 2}, {"value": [7.286934852600098], "step": 3}, {"value": [7.58233642578125], "step": 4}, {"value": [10.010172843933105], "step": 5}, {"value": [9.684813499450684], "step": 6}, {"value": [9.938953399658203], "step": 7}, {"value": [4.471571922302246], "step": 8}, {"value": [3.5283331871032715], "step": 9}, {"value": [2.376758337020874], "step": 10}, {"value": [8.677486419677734], "step": 11}, {"value": [3.2494747638702393], "step": 12}, {"value": [4.219418525695801], "step": 13}, {"value": [2.0071463584899902], "step": 14}, {"value": [2.4326252937316895], "step": 15}, {"value": [1.6082475185394287], "step": 16}, {"value": [0.8163304328918457], "step": 17}, {"value": [2.18752121925354], "step": 18}, {"value": [1.844802737236023], "step": 19}, {"value": [1.0817985534667969], "step": 20}, {"value": [1.0530251264572144], "step": 21}, {"value": [1.4912242889404297], "step": 22}, {"value": [0.7825552821159363], "step": 23}, {"value": [0.4967135190963745], "step": 24}, {"value": [0.3245268762111664], "step": 25}, {"value": [0.23619192838668823], "step": 26}, {"value": [0.16862867772579193], "step": 27}, {"value": [0.1410450041294098], "step": 28}, {"value": [0.12101196497678757], "step": 29}]}, "val_mean_squared_error": {"direction": "min", "observations": [{"value": [14.118906021118164], "step": 0}, {"value": [57.84541320800781], "step": 1}, {"value": [7.574304103851318], "step": 2}, {"value": [7.286934852600098], "step": 3}, {"value": [7.58233642578125], "step": 4}, {"value": [10.010172843933105], "step": 5}, {"value": [9.684813499450684], "step": 6}, {"value": [9.938953399658203], "step": 7}, {"value": [4.471571922302246], "step": 8}, {"value": [3.5283331871032715], "step": 9}, {"value": [2.376758337020874], "step": 10}, {"value": [8.677486419677734], "step": 11}, {"value": [3.2494747638702393], "step": 12}, {"value": [4.219418525695801], "step": 13}, {"value": [2.0071463584899902], "step": 14}, {"value": [2.4326252937316895], "step": 15}, {"value": [1.6082475185394287], "step": 16}, {"value": [0.8163304328918457], "step": 17}, {"value": [2.18752121925354], "step": 18}, {"value": [1.844802737236023], "step": 19}, {"value": [1.0817985534667969], "step": 20}, {"value": [1.0530251264572144], "step": 21}, {"value": [1.4912242889404297], "step": 22}, {"value": [0.7825552821159363], "step": 23}, {"value": [0.4967135190963745], "step": 24}, {"value": [0.3245268762111664], "step": 25}, {"value": [0.23619192838668823], "step": 26}, {"value": [0.16862867772579193], "step": 27}, {"value": [0.1410450041294098], "step": 28}, {"value": [0.12101196497678757], "step": 29}]}}}, "score": 0.12101196497678757, "best_step": 29, "status": "COMPLETED"}